{"textures":{"7":"minecraft:item/microphones/ttpd"},"elements":[{"from":[7.363999999999976,3.6949999999999994,6.364],"to":[8.613999999999976,8.695,7.614],"rotation":{"angle":0,"axis":"y","origin":[2.3389999999999986,7.1075,12.544]},"faces":{"north":{"uv":[0,0,1.5,5],"texture":"#7"},"east":{"uv":[2,0,3.5,5],"texture":"#7"},"south":{"uv":[4,0,5.5,5],"texture":"#7"},"west":{"uv":[0,5,1.5,10],"texture":"#7"},"up":{"uv":[7.5,9.5,6,8],"texture":"#7"},"down":{"uv":[9.5,6,8,7.5],"texture":"#7"}}},{"from":[7.01400000000001,8.695,6.014],"to":[9.01400000000001,10.895,8.014],"rotation":{"angle":0,"axis":"y","origin":[2.3389999999999986,7.1075,12.544]},"faces":{"north":{"uv":[2,5,4,7.5],"texture":"#7"},"east":{"uv":[4,5,6,7.5],"texture":"#7"},"south":{"uv":[6,0,8,2.5],"texture":"#7"},"west":{"uv":[6,3,8,5.5],"texture":"#7"},"up":{"uv":[8,8,6,6],"texture":"#7"},"down":{"uv":[10,0,8,2],"texture":"#7"}}},{"from":[6.913999999999987,9.695,5.914],"to":[9.113999999999976,9.895,8.114],"rotation":{"angle":0,"axis":"y","origin":[2.3389999999999986,7.1075,12.544]},"faces":{"north":{"uv":[8,8,10,8.5],"texture":"#7"},"east":{"uv":[8,9,10,9.5],"texture":"#7"},"south":{"uv":[0,10,2,10.5],"texture":"#7"},"west":{"uv":[10,0,12,0.5],"texture":"#7"},"up":{"uv":[4,10,2,8],"texture":"#7"},"down":{"uv":[10,2,8,4],"texture":"#7"}}},{"from":[7.113999999999976,10.895,6.114],"to":[8.863999999999976,11.145,7.864],"rotation":{"angle":0,"axis":"y","origin":[2.3389999999999986,7.1075,12.544]},"faces":{"north":{"uv":[10,1,12,1.5],"texture":"#7"},"east":{"uv":[2,10,4,10.5],"texture":"#7"},"south":{"uv":[10,2,12,2.5],"texture":"#7"},"west":{"uv":[10,3,12,3.5],"texture":"#7"},"up":{"uv":[6,10,4,8],"texture":"#7"},"down":{"uv":[10,4,8,6],"texture":"#7"}}},{"from":[7.493999999999971,2.6949999999999994,6.494],"to":[8.493999999999971,3.6949999999999994,7.494],"rotation":{"angle":0,"axis":"y","origin":[2.3389999999999986,7.1075,12.544]},"faces":{"north":{"uv":[4,10,5,11],"texture":"#7"},"east":{"uv":[10,4,11,5],"texture":"#7"},"south":{"uv":[5,10,6,11],"texture":"#7"},"west":{"uv":[10,5,11,6],"texture":"#7"},"up":{"uv":[7,11,6,10],"texture":"#7"},"down":{"uv":[11,6,10,7],"texture":"#7"}}}],"display":{"head":{"rotation":[0,180,0]}}}