{"parent":"item/generated","textures":{"layer0":"minecraft:item/green_dye"},"overrides":[{"predicate":{"custom_model_data":1},"model":"item/animated_java_empty"},{"predicate":{"custom_model_data":2},"model":"animated_java:item/microphone/left_straight"},{"predicate":{"custom_model_data":3},"model":"animated_java:item/microphone/left_bend"},{"predicate":{"custom_model_data":4},"model":"animated_java:item/microphone/right_straight"},{"predicate":{"custom_model_data":5},"model":"animated_java:item/microphone/microphone"},{"predicate":{"custom_model_data":6},"model":"animated_java:item/microphone/right_bend"},{"predicate":{"custom_model_data":7},"model":"animated_java:item/microphone/head"},{"predicate":{"custom_model_data":8},"model":"animated_java:item/microphone/outfit"},{"predicate":{"custom_model_data":9},"model":"animated_java:item/microphone/chest"},{"predicate":{"custom_model_data":10},"model":"animated_java:item/microphone/right_leg"},{"predicate":{"custom_model_data":11},"model":"animated_java:item/microphone/left_leg"},{"predicate":{"custom_model_data":12},"model":"animated_java:item/microphone/bad_blazer/left_straight"},{"predicate":{"custom_model_data":13},"model":"animated_java:item/microphone/bad_blazer/left_bend"},{"predicate":{"custom_model_data":14},"model":"animated_java:item/microphone/bad_blazer/right_straight"},{"predicate":{"custom_model_data":15},"model":"animated_java:item/microphone/bad_blazer/microphone"},{"predicate":{"custom_model_data":16},"model":"animated_java:item/microphone/bad_blazer/right_bend"},{"predicate":{"custom_model_data":17},"model":"animated_java:item/microphone/bad_blazer/head"},{"predicate":{"custom_model_data":18},"model":"animated_java:item/microphone/bad_blazer/outfit"},{"predicate":{"custom_model_data":19},"model":"animated_java:item/microphone/bad_blazer/chest"},{"predicate":{"custom_model_data":20},"model":"animated_java:item/microphone/bad_blazer/right_leg"},{"predicate":{"custom_model_data":21},"model":"animated_java:item/microphone/bad_blazer/left_leg"},{"predicate":{"custom_model_data":22},"model":"animated_java:item/microphone/fearless_blazer/left_straight"},{"predicate":{"custom_model_data":23},"model":"animated_java:item/microphone/fearless_blazer/left_bend"},{"predicate":{"custom_model_data":24},"model":"animated_java:item/microphone/fearless_blazer/right_straight"},{"predicate":{"custom_model_data":25},"model":"animated_java:item/microphone/fearless_blazer/microphone"},{"predicate":{"custom_model_data":26},"model":"animated_java:item/microphone/fearless_blazer/right_bend"},{"predicate":{"custom_model_data":27},"model":"animated_java:item/microphone/fearless_blazer/head"},{"predicate":{"custom_model_data":28},"model":"animated_java:item/microphone/fearless_blazer/outfit"},{"predicate":{"custom_model_data":29},"model":"animated_java:item/microphone/fearless_blazer/chest"},{"predicate":{"custom_model_data":30},"model":"animated_java:item/microphone/fearless_blazer/right_leg"},{"predicate":{"custom_model_data":31},"model":"animated_java:item/microphone/fearless_blazer/left_leg"},{"predicate":{"custom_model_data":32},"model":"animated_java:item/microphone/golden_lover/left_straight"},{"predicate":{"custom_model_data":33},"model":"animated_java:item/microphone/golden_lover/left_bend"},{"predicate":{"custom_model_data":34},"model":"animated_java:item/microphone/golden_lover/right_straight"},{"predicate":{"custom_model_data":35},"model":"animated_java:item/microphone/golden_lover/microphone"},{"predicate":{"custom_model_data":36},"model":"animated_java:item/microphone/golden_lover/right_bend"},{"predicate":{"custom_model_data":37},"model":"animated_java:item/microphone/golden_lover/head"},{"predicate":{"custom_model_data":38},"model":"animated_java:item/microphone/golden_lover/outfit"},{"predicate":{"custom_model_data":39},"model":"animated_java:item/microphone/golden_lover/chest"},{"predicate":{"custom_model_data":40},"model":"animated_java:item/microphone/golden_lover/right_leg"},{"predicate":{"custom_model_data":41},"model":"animated_java:item/microphone/golden_lover/left_leg"},{"predicate":{"custom_model_data":42},"model":"animated_java:item/microphone/heart_lover/left_straight"},{"predicate":{"custom_model_data":43},"model":"animated_java:item/microphone/heart_lover/left_bend"},{"predicate":{"custom_model_data":44},"model":"animated_java:item/microphone/heart_lover/right_straight"},{"predicate":{"custom_model_data":45},"model":"animated_java:item/microphone/heart_lover/microphone"},{"predicate":{"custom_model_data":46},"model":"animated_java:item/microphone/heart_lover/right_bend"},{"predicate":{"custom_model_data":47},"model":"animated_java:item/microphone/heart_lover/head"},{"predicate":{"custom_model_data":48},"model":"animated_java:item/microphone/heart_lover/outfit"},{"predicate":{"custom_model_data":49},"model":"animated_java:item/microphone/heart_lover/chest"},{"predicate":{"custom_model_data":50},"model":"animated_java:item/microphone/heart_lover/right_leg"},{"predicate":{"custom_model_data":51},"model":"animated_java:item/microphone/heart_lover/left_leg"},{"predicate":{"custom_model_data":52},"model":"animated_java:item/microphone/sunset_lover/left_straight"},{"predicate":{"custom_model_data":53},"model":"animated_java:item/microphone/sunset_lover/left_bend"},{"predicate":{"custom_model_data":54},"model":"animated_java:item/microphone/sunset_lover/right_straight"},{"predicate":{"custom_model_data":55},"model":"animated_java:item/microphone/sunset_lover/microphone"},{"predicate":{"custom_model_data":56},"model":"animated_java:item/microphone/sunset_lover/right_bend"},{"predicate":{"custom_model_data":57},"model":"animated_java:item/microphone/sunset_lover/head"},{"predicate":{"custom_model_data":58},"model":"animated_java:item/microphone/sunset_lover/outfit"},{"predicate":{"custom_model_data":59},"model":"animated_java:item/microphone/sunset_lover/chest"},{"predicate":{"custom_model_data":60},"model":"animated_java:item/microphone/sunset_lover/right_leg"},{"predicate":{"custom_model_data":61},"model":"animated_java:item/microphone/sunset_lover/left_leg"},{"predicate":{"custom_model_data":62},"model":"animated_java:item/microphone/violet_lover/left_straight"},{"predicate":{"custom_model_data":63},"model":"animated_java:item/microphone/violet_lover/left_bend"},{"predicate":{"custom_model_data":64},"model":"animated_java:item/microphone/violet_lover/right_straight"},{"predicate":{"custom_model_data":65},"model":"animated_java:item/microphone/violet_lover/microphone"},{"predicate":{"custom_model_data":66},"model":"animated_java:item/microphone/violet_lover/right_bend"},{"predicate":{"custom_model_data":67},"model":"animated_java:item/microphone/violet_lover/head"},{"predicate":{"custom_model_data":68},"model":"animated_java:item/microphone/violet_lover/outfit"},{"predicate":{"custom_model_data":69},"model":"animated_java:item/microphone/violet_lover/chest"},{"predicate":{"custom_model_data":70},"model":"animated_java:item/microphone/violet_lover/right_leg"},{"predicate":{"custom_model_data":71},"model":"animated_java:item/microphone/violet_lover/left_leg"},{"predicate":{"custom_model_data":72},"model":"animated_java:item/lover_microphone/left_straight"},{"predicate":{"custom_model_data":73},"model":"animated_java:item/lover_microphone/left_bend"},{"predicate":{"custom_model_data":74},"model":"animated_java:item/lover_microphone/right_straight"},{"predicate":{"custom_model_data":75},"model":"animated_java:item/lover_microphone/microphone"},{"predicate":{"custom_model_data":76},"model":"animated_java:item/lover_microphone/right_bend"},{"predicate":{"custom_model_data":77},"model":"animated_java:item/lover_microphone/head"},{"predicate":{"custom_model_data":78},"model":"animated_java:item/lover_microphone/outfit"},{"predicate":{"custom_model_data":79},"model":"animated_java:item/lover_microphone/chest"},{"predicate":{"custom_model_data":80},"model":"animated_java:item/lover_microphone/right_leg"},{"predicate":{"custom_model_data":81},"model":"animated_java:item/lover_microphone/left_leg"},{"predicate":{"custom_model_data":82},"model":"animated_java:item/lover_microphone/bad_blazer/left_straight"},{"predicate":{"custom_model_data":83},"model":"animated_java:item/lover_microphone/bad_blazer/left_bend"},{"predicate":{"custom_model_data":84},"model":"animated_java:item/lover_microphone/bad_blazer/right_straight"},{"predicate":{"custom_model_data":85},"model":"animated_java:item/lover_microphone/bad_blazer/microphone"},{"predicate":{"custom_model_data":86},"model":"animated_java:item/lover_microphone/bad_blazer/right_bend"},{"predicate":{"custom_model_data":87},"model":"animated_java:item/lover_microphone/bad_blazer/head"},{"predicate":{"custom_model_data":88},"model":"animated_java:item/lover_microphone/bad_blazer/outfit"},{"predicate":{"custom_model_data":89},"model":"animated_java:item/lover_microphone/bad_blazer/chest"},{"predicate":{"custom_model_data":90},"model":"animated_java:item/lover_microphone/bad_blazer/right_leg"},{"predicate":{"custom_model_data":91},"model":"animated_java:item/lover_microphone/bad_blazer/left_leg"},{"predicate":{"custom_model_data":92},"model":"animated_java:item/lover_microphone/fearless_blazer/left_straight"},{"predicate":{"custom_model_data":93},"model":"animated_java:item/lover_microphone/fearless_blazer/left_bend"},{"predicate":{"custom_model_data":94},"model":"animated_java:item/lover_microphone/fearless_blazer/right_straight"},{"predicate":{"custom_model_data":95},"model":"animated_java:item/lover_microphone/fearless_blazer/microphone"},{"predicate":{"custom_model_data":96},"model":"animated_java:item/lover_microphone/fearless_blazer/right_bend"},{"predicate":{"custom_model_data":97},"model":"animated_java:item/lover_microphone/fearless_blazer/head"},{"predicate":{"custom_model_data":98},"model":"animated_java:item/lover_microphone/fearless_blazer/outfit"},{"predicate":{"custom_model_data":99},"model":"animated_java:item/lover_microphone/fearless_blazer/chest"},{"predicate":{"custom_model_data":100},"model":"animated_java:item/lover_microphone/fearless_blazer/right_leg"},{"predicate":{"custom_model_data":101},"model":"animated_java:item/lover_microphone/fearless_blazer/left_leg"},{"predicate":{"custom_model_data":102},"model":"animated_java:item/lover_microphone/golden_lover/left_straight"},{"predicate":{"custom_model_data":103},"model":"animated_java:item/lover_microphone/golden_lover/left_bend"},{"predicate":{"custom_model_data":104},"model":"animated_java:item/lover_microphone/golden_lover/right_straight"},{"predicate":{"custom_model_data":105},"model":"animated_java:item/lover_microphone/golden_lover/microphone"},{"predicate":{"custom_model_data":106},"model":"animated_java:item/lover_microphone/golden_lover/right_bend"},{"predicate":{"custom_model_data":107},"model":"animated_java:item/lover_microphone/golden_lover/head"},{"predicate":{"custom_model_data":108},"model":"animated_java:item/lover_microphone/golden_lover/outfit"},{"predicate":{"custom_model_data":109},"model":"animated_java:item/lover_microphone/golden_lover/chest"},{"predicate":{"custom_model_data":110},"model":"animated_java:item/lover_microphone/golden_lover/right_leg"},{"predicate":{"custom_model_data":111},"model":"animated_java:item/lover_microphone/golden_lover/left_leg"},{"predicate":{"custom_model_data":112},"model":"animated_java:item/lover_microphone/heart_lover/left_straight"},{"predicate":{"custom_model_data":113},"model":"animated_java:item/lover_microphone/heart_lover/left_bend"},{"predicate":{"custom_model_data":114},"model":"animated_java:item/lover_microphone/heart_lover/right_straight"},{"predicate":{"custom_model_data":115},"model":"animated_java:item/lover_microphone/heart_lover/microphone"},{"predicate":{"custom_model_data":116},"model":"animated_java:item/lover_microphone/heart_lover/right_bend"},{"predicate":{"custom_model_data":117},"model":"animated_java:item/lover_microphone/heart_lover/head"},{"predicate":{"custom_model_data":118},"model":"animated_java:item/lover_microphone/heart_lover/outfit"},{"predicate":{"custom_model_data":119},"model":"animated_java:item/lover_microphone/heart_lover/chest"},{"predicate":{"custom_model_data":120},"model":"animated_java:item/lover_microphone/heart_lover/right_leg"},{"predicate":{"custom_model_data":121},"model":"animated_java:item/lover_microphone/heart_lover/left_leg"},{"predicate":{"custom_model_data":122},"model":"animated_java:item/lover_microphone/models_blazer/left_straight"},{"predicate":{"custom_model_data":123},"model":"animated_java:item/lover_microphone/models_blazer/left_bend"},{"predicate":{"custom_model_data":124},"model":"animated_java:item/lover_microphone/models_blazer/right_straight"},{"predicate":{"custom_model_data":125},"model":"animated_java:item/lover_microphone/models_blazer/microphone"},{"predicate":{"custom_model_data":126},"model":"animated_java:item/lover_microphone/models_blazer/right_bend"},{"predicate":{"custom_model_data":127},"model":"animated_java:item/lover_microphone/models_blazer/head"},{"predicate":{"custom_model_data":128},"model":"animated_java:item/lover_microphone/models_blazer/outfit"},{"predicate":{"custom_model_data":129},"model":"animated_java:item/lover_microphone/models_blazer/chest"},{"predicate":{"custom_model_data":130},"model":"animated_java:item/lover_microphone/models_blazer/right_leg"},{"predicate":{"custom_model_data":131},"model":"animated_java:item/lover_microphone/models_blazer/left_leg"},{"predicate":{"custom_model_data":132},"model":"animated_java:item/lover_microphone/sunset_lover/left_straight"},{"predicate":{"custom_model_data":133},"model":"animated_java:item/lover_microphone/sunset_lover/left_bend"},{"predicate":{"custom_model_data":134},"model":"animated_java:item/lover_microphone/sunset_lover/right_straight"},{"predicate":{"custom_model_data":135},"model":"animated_java:item/lover_microphone/sunset_lover/microphone"},{"predicate":{"custom_model_data":136},"model":"animated_java:item/lover_microphone/sunset_lover/right_bend"},{"predicate":{"custom_model_data":137},"model":"animated_java:item/lover_microphone/sunset_lover/head"},{"predicate":{"custom_model_data":138},"model":"animated_java:item/lover_microphone/sunset_lover/outfit"},{"predicate":{"custom_model_data":139},"model":"animated_java:item/lover_microphone/sunset_lover/chest"},{"predicate":{"custom_model_data":140},"model":"animated_java:item/lover_microphone/sunset_lover/right_leg"},{"predicate":{"custom_model_data":141},"model":"animated_java:item/lover_microphone/sunset_lover/left_leg"},{"predicate":{"custom_model_data":142},"model":"animated_java:item/lover_microphone/violet_lover/left_straight"},{"predicate":{"custom_model_data":143},"model":"animated_java:item/lover_microphone/violet_lover/left_bend"},{"predicate":{"custom_model_data":144},"model":"animated_java:item/lover_microphone/violet_lover/right_straight"},{"predicate":{"custom_model_data":145},"model":"animated_java:item/lover_microphone/violet_lover/microphone"},{"predicate":{"custom_model_data":146},"model":"animated_java:item/lover_microphone/violet_lover/right_bend"},{"predicate":{"custom_model_data":147},"model":"animated_java:item/lover_microphone/violet_lover/head"},{"predicate":{"custom_model_data":148},"model":"animated_java:item/lover_microphone/violet_lover/outfit"},{"predicate":{"custom_model_data":149},"model":"animated_java:item/lover_microphone/violet_lover/chest"},{"predicate":{"custom_model_data":150},"model":"animated_java:item/lover_microphone/violet_lover/right_leg"},{"predicate":{"custom_model_data":151},"model":"animated_java:item/lover_microphone/violet_lover/left_leg"}],"animated_java":{"rigs":{"microphone":{"used_ids":[2,3,4,5,6,7,8,9,10,11,12,13,14,15,16,17,18,19,20,21,22,23,24,25,26,27,28,29,30,31,32,33,34,35,36,37,38,39,40,41,42,43,44,45,46,47,48,49,50,51,52,53,54,55,56,57,58,59,60,61,62,63,64,65,66,67,68,69,70,71]},"lover_microphone":{"used_ids":[72,73,74,75,76,77,78,79,80,81,82,83,84,85,86,87,88,89,90,91,92,93,94,95,96,97,98,99,100,101,102,103,104,105,106,107,108,109,110,111,112,113,114,115,116,117,118,119,120,121,122,123,124,125,126,127,128,129,130,131,132,133,134,135,136,137,138,139,140,141,142,143,144,145,146,147,148,149,150,151]}}}}